sesam/__init__.py
sesam/wsdl/StudentService_2.0_production.wsdl
sesam-2.1.1.dist-info/DESCRIPTION.rst
sesam-2.1.1.dist-info/METADATA
sesam-2.1.1.dist-info/RECORD
sesam-2.1.1.dist-info/WHEEL
sesam-2.1.1.dist-info/metadata.json
sesam-2.1.1.dist-info/top_level.txt
