Metadata-Version: 2.0
Name: sesam
Version: 2.1.1
Summary: UNKNOWN
Home-page: https://github.com/ovidner/python-sesam
Author: Olle Vidner
Author-email: olle@vidner.se
License: MIT
Platform: UNKNOWN
Requires-Dist: attrs (==17.*)
Requires-Dist: zeep (==2.*)
